{
	"_type": "export",
	"__export_format": 3,
	"__export_date": "2018-09-17T17:36:29.752Z",
	"__export_source": "insomnia.desktop.app:v6.0.2",
	"resources": [
		{
			"_id": "wrk_51516313f77a4d3c9c686bb3d3fe2930",
			"created": 1536860409964,
			"description": "",
			"modified": 1536860409964,
			"name": "Sudoku",
			"parentId": null,
			"_type": "workspace"
		},
		{
			"_id": "env_bbc403568a7041aeb26604e66faa71cf",
			"color": null,
			"created": 1536860409984,
			"data": {},
			"isPrivate": false,
			"metaSortKey": 1536860409984,
			"modified": 1536860420145,
			"name": "New Environment",
			"parentId": "wrk_51516313f77a4d3c9c686bb3d3fe2930",
			"_type": "environment"
		},
		{
			"_id": "jar_e35c86f6113746bfa17d3ab4621efb74",
			"cookies": [],
			"created": 1536860409988,
			"modified": 1536860409988,
			"name": "Default Jar",
			"parentId": "wrk_51516313f77a4d3c9c686bb3d3fe2930",
			"_type": "cookie_jar"
		},
		{
			"_id": "req_79bf50f703b34bc291e765f5244edf3e",
			"authentication": {},
			"body": {},
			"created": 1536860461994,
			"description": "",
			"headers": [],
			"isPrivate": false,
			"metaSortKey": -1536860461994,
			"method": "GET",
			"modified": 1537205706139,
			"name": "Blank Grid",
			"parameters": [],
			"parentId": "wrk_51516313f77a4d3c9c686bb3d3fe2930",
			"settingDisableRenderRequestBody": false,
			"settingEncodeUrl": true,
			"settingMaxTimelineDataSize": 1000,
			"settingRebuildPath": true,
			"settingSendCookies": true,
			"settingStoreCookies": true,
			"url": "localhost:3000/grid",
			"_type": "request"
		},
		{
			"_id": "req_8688bd25d39b4799a3f1293674c861ee",
			"authentication": {},
			"body": {},
			"created": 1536860484697,
			"description": "",
			"headers": [],
			"isPrivate": false,
			"metaSortKey": -1536860484697,
			"method": "GET",
			"modified": 1537205704072,
			"name": "Health Check",
			"parameters": [],
			"parentId": "wrk_51516313f77a4d3c9c686bb3d3fe2930",
			"settingDisableRenderRequestBody": false,
			"settingEncodeUrl": true,
			"settingMaxTimelineDataSize": 1000,
			"settingRebuildPath": true,
			"settingSendCookies": true,
			"settingStoreCookies": true,
			"url": "localhost:3000/health",
			"_type": "request"
		},
		{
			"_id": "req_438ff03eba954490bb166773b4f6b4ab",
			"authentication": {},
			"body": {},
			"created": 1536955353970,
			"description": "",
			"headers": [],
			"isPrivate": false,
			"metaSortKey": -1536955353970,
			"method": "GET",
			"modified": 1537205701311,
			"name": "Grid by Id",
			"parameters": [],
			"parentId": "wrk_51516313f77a4d3c9c686bb3d3fe2930",
			"settingDisableRenderRequestBody": false,
			"settingEncodeUrl": true,
			"settingMaxTimelineDataSize": 1000,
			"settingRebuildPath": true,
			"settingSendCookies": true,
			"settingStoreCookies": true,
			"url": "localhost:3000/grid/0",
			"_type": "request"
		},
		{
			"_id": "req_a2d4ded91300497b8c564cabe964784f",
			"authentication": {},
			"body": {
				"mimeType": "application/json",
				"text": "{\n\t\"gridId\": 0,\n\t\"solved\": false,\n\t\"cells\": [\n\t\t{\n\t\t\t\"revealed\": false,\n\t\t\t\"cellId\": 0,\n\t\t\t\"row\": 0,\n\t\t\t\"userValue\": 0,\n\t\t\t\"col\": 0,\n\t\t\t\"realValue\": 0\n\t\t},\n\t\t{\n\t\t\t\"revealed\": false,\n\t\t\t\"cellId\": 1,\n\t\t\t\"row\": 0,\n\t\t\t\"userValue\": 0,\n\t\t\t\"col\": 1,\n\t\t\t\"realValue\": 0\n\t\t},\n\t\t{\n\t\t\t\"revealed\": false,\n\t\t\t\"cellId\": 2,\n\t\t\t\"row\": 0,\n\t\t\t\"userValue\": 0,\n\t\t\t\"col\": 2,\n\t\t\t\"realValue\": 0\n\t\t},\n\t\t{\n\t\t\t\"revealed\": false,\n\t\t\t\"cellId\": 3,\n\t\t\t\"row\": 0,\n\t\t\t\"userValue\": 0,\n\t\t\t\"col\": 3,\n\t\t\t\"realValue\": 0\n\t\t},\n\t\t{\n\t\t\t\"revealed\": false,\n\t\t\t\"cellId\": 4,\n\t\t\t\"row\": 0,\n\t\t\t\"userValue\": 0,\n\t\t\t\"col\": 4,\n\t\t\t\"realValue\": 0\n\t\t},\n\t\t{\n\t\t\t\"revealed\": false,\n\t\t\t\"cellId\": 5,\n\t\t\t\"row\": 0,\n\t\t\t\"userValue\": 0,\n\t\t\t\"col\": 5,\n\t\t\t\"realValue\": 0\n\t\t},\n\t\t{\n\t\t\t\"revealed\": false,\n\t\t\t\"cellId\": 6,\n\t\t\t\"row\": 0,\n\t\t\t\"userValue\": 0,\n\t\t\t\"col\": 6,\n\t\t\t\"realValue\": 0\n\t\t},\n\t\t{\n\t\t\t\"revealed\": false,\n\t\t\t\"cellId\": 7,\n\t\t\t\"row\": 0,\n\t\t\t\"userValue\": 0,\n\t\t\t\"col\": 7,\n\t\t\t\"realValue\": 0\n\t\t},\n\t\t{\n\t\t\t\"revealed\": false,\n\t\t\t\"cellId\": 8,\n\t\t\t\"row\": 0,\n\t\t\t\"userValue\": 0,\n\t\t\t\"col\": 8,\n\t\t\t\"realValue\": 0\n\t\t},\n\t\t{\n\t\t\t\"revealed\": false,\n\t\t\t\"cellId\": 9,\n\t\t\t\"row\": 1,\n\t\t\t\"userValue\": 0,\n\t\t\t\"col\": 0,\n\t\t\t\"realValue\": 0\n\t\t},\n\t\t{\n\t\t\t\"revealed\": false,\n\t\t\t\"cellId\": 10,\n\t\t\t\"row\": 1,\n\t\t\t\"userValue\": 0,\n\t\t\t\"col\": 1,\n\t\t\t\"realValue\": 0\n\t\t},\n\t\t{\n\t\t\t\"revealed\": false,\n\t\t\t\"cellId\": 11,\n\t\t\t\"row\": 1,\n\t\t\t\"userValue\": 0,\n\t\t\t\"col\": 2,\n\t\t\t\"realValue\": 0\n\t\t},\n\t\t{\n\t\t\t\"revealed\": false,\n\t\t\t\"cellId\": 12,\n\t\t\t\"row\": 1,\n\t\t\t\"userValue\": 0,\n\t\t\t\"col\": 3,\n\t\t\t\"realValue\": 0\n\t\t},\n\t\t{\n\t\t\t\"revealed\": false,\n\t\t\t\"cellId\": 13,\n\t\t\t\"row\": 1,\n\t\t\t\"userValue\": 0,\n\t\t\t\"col\": 4,\n\t\t\t\"realValue\": 0\n\t\t},\n\t\t{\n\t\t\t\"revealed\": false,\n\t\t\t\"cellId\": 14,\n\t\t\t\"row\": 1,\n\t\t\t\"userValue\": 0,\n\t\t\t\"col\": 5,\n\t\t\t\"realValue\": 0\n\t\t},\n\t\t{\n\t\t\t\"revealed\": false,\n\t\t\t\"cellId\": 15,\n\t\t\t\"row\": 1,\n\t\t\t\"userValue\": 0,\n\t\t\t\"col\": 6,\n\t\t\t\"realValue\": 0\n\t\t},\n\t\t{\n\t\t\t\"revealed\": false,\n\t\t\t\"cellId\": 16,\n\t\t\t\"row\": 1,\n\t\t\t\"userValue\": 0,\n\t\t\t\"col\": 7,\n\t\t\t\"realValue\": 0\n\t\t},\n\t\t{\n\t\t\t\"revealed\": false,\n\t\t\t\"cellId\": 17,\n\t\t\t\"row\": 1,\n\t\t\t\"userValue\": 0,\n\t\t\t\"col\": 8,\n\t\t\t\"realValue\": 0\n\t\t},\n\t\t{\n\t\t\t\"revealed\": false,\n\t\t\t\"cellId\": 18,\n\t\t\t\"row\": 2,\n\t\t\t\"userValue\": 0,\n\t\t\t\"col\": 0,\n\t\t\t\"realValue\": 0\n\t\t},\n\t\t{\n\t\t\t\"revealed\": false,\n\t\t\t\"cellId\": 19,\n\t\t\t\"row\": 2,\n\t\t\t\"userValue\": 0,\n\t\t\t\"col\": 1,\n\t\t\t\"realValue\": 0\n\t\t},\n\t\t{\n\t\t\t\"revealed\": false,\n\t\t\t\"cellId\": 20,\n\t\t\t\"row\": 2,\n\t\t\t\"userValue\": 0,\n\t\t\t\"col\": 2,\n\t\t\t\"realValue\": 0\n\t\t},\n\t\t{\n\t\t\t\"revealed\": false,\n\t\t\t\"cellId\": 21,\n\t\t\t\"row\": 2,\n\t\t\t\"userValue\": 0,\n\t\t\t\"col\": 3,\n\t\t\t\"realValue\": 0\n\t\t},\n\t\t{\n\t\t\t\"revealed\": false,\n\t\t\t\"cellId\": 22,\n\t\t\t\"row\": 2,\n\t\t\t\"userValue\": 0,\n\t\t\t\"col\": 4,\n\t\t\t\"realValue\": 0\n\t\t},\n\t\t{\n\t\t\t\"revealed\": false,\n\t\t\t\"cellId\": 23,\n\t\t\t\"row\": 2,\n\t\t\t\"userValue\": 0,\n\t\t\t\"col\": 5,\n\t\t\t\"realValue\": 0\n\t\t},\n\t\t{\n\t\t\t\"revealed\": false,\n\t\t\t\"cellId\": 24,\n\t\t\t\"row\": 2,\n\t\t\t\"userValue\": 0,\n\t\t\t\"col\": 6,\n\t\t\t\"realValue\": 0\n\t\t},\n\t\t{\n\t\t\t\"revealed\": false,\n\t\t\t\"cellId\": 25,\n\t\t\t\"row\": 2,\n\t\t\t\"userValue\": 0,\n\t\t\t\"col\": 7,\n\t\t\t\"realValue\": 0\n\t\t},\n\t\t{\n\t\t\t\"revealed\": false,\n\t\t\t\"cellId\": 26,\n\t\t\t\"row\": 2,\n\t\t\t\"userValue\": 0,\n\t\t\t\"col\": 8,\n\t\t\t\"realValue\": 0\n\t\t},\n\t\t{\n\t\t\t\"revealed\": false,\n\t\t\t\"cellId\": 27,\n\t\t\t\"row\": 3,\n\t\t\t\"userValue\": 0,\n\t\t\t\"col\": 0,\n\t\t\t\"realValue\": 0\n\t\t},\n\t\t{\n\t\t\t\"revealed\": false,\n\t\t\t\"cellId\": 28,\n\t\t\t\"row\": 3,\n\t\t\t\"userValue\": 0,\n\t\t\t\"col\": 1,\n\t\t\t\"realValue\": 0\n\t\t},\n\t\t{\n\t\t\t\"revealed\": false,\n\t\t\t\"cellId\": 29,\n\t\t\t\"row\": 3,\n\t\t\t\"userValue\": 0,\n\t\t\t\"col\": 2,\n\t\t\t\"realValue\": 0\n\t\t},\n\t\t{\n\t\t\t\"revealed\": false,\n\t\t\t\"cellId\": 30,\n\t\t\t\"row\": 3,\n\t\t\t\"userValue\": 0,\n\t\t\t\"col\": 3,\n\t\t\t\"realValue\": 0\n\t\t},\n\t\t{\n\t\t\t\"revealed\": false,\n\t\t\t\"cellId\": 31,\n\t\t\t\"row\": 3,\n\t\t\t\"userValue\": 0,\n\t\t\t\"col\": 4,\n\t\t\t\"realValue\": 0\n\t\t},\n\t\t{\n\t\t\t\"revealed\": false,\n\t\t\t\"cellId\": 32,\n\t\t\t\"row\": 3,\n\t\t\t\"userValue\": 0,\n\t\t\t\"col\": 5,\n\t\t\t\"realValue\": 0\n\t\t},\n\t\t{\n\t\t\t\"revealed\": false,\n\t\t\t\"cellId\": 33,\n\t\t\t\"row\": 3,\n\t\t\t\"userValue\": 0,\n\t\t\t\"col\": 6,\n\t\t\t\"realValue\": 0\n\t\t},\n\t\t{\n\t\t\t\"revealed\": false,\n\t\t\t\"cellId\": 34,\n\t\t\t\"row\": 3,\n\t\t\t\"userValue\": 0,\n\t\t\t\"col\": 7,\n\t\t\t\"realValue\": 0\n\t\t},\n\t\t{\n\t\t\t\"revealed\": false,\n\t\t\t\"cellId\": 35,\n\t\t\t\"row\": 3,\n\t\t\t\"userValue\": 0,\n\t\t\t\"col\": 8,\n\t\t\t\"realValue\": 0\n\t\t},\n\t\t{\n\t\t\t\"revealed\": false,\n\t\t\t\"cellId\": 36,\n\t\t\t\"row\": 4,\n\t\t\t\"userValue\": 0,\n\t\t\t\"col\": 0,\n\t\t\t\"realValue\": 0\n\t\t},\n\t\t{\n\t\t\t\"revealed\": false,\n\t\t\t\"cellId\": 37,\n\t\t\t\"row\": 4,\n\t\t\t\"userValue\": 0,\n\t\t\t\"col\": 1,\n\t\t\t\"realValue\": 0\n\t\t},\n\t\t{\n\t\t\t\"revealed\": false,\n\t\t\t\"cellId\": 38,\n\t\t\t\"row\": 4,\n\t\t\t\"userValue\": 0,\n\t\t\t\"col\": 2,\n\t\t\t\"realValue\": 0\n\t\t},\n\t\t{\n\t\t\t\"revealed\": false,\n\t\t\t\"cellId\": 39,\n\t\t\t\"row\": 4,\n\t\t\t\"userValue\": 0,\n\t\t\t\"col\": 3,\n\t\t\t\"realValue\": 0\n\t\t},\n\t\t{\n\t\t\t\"revealed\": false,\n\t\t\t\"cellId\": 40,\n\t\t\t\"row\": 4,\n\t\t\t\"userValue\": 0,\n\t\t\t\"col\": 4,\n\t\t\t\"realValue\": 0\n\t\t},\n\t\t{\n\t\t\t\"revealed\": false,\n\t\t\t\"cellId\": 41,\n\t\t\t\"row\": 4,\n\t\t\t\"userValue\": 0,\n\t\t\t\"col\": 5,\n\t\t\t\"realValue\": 0\n\t\t},\n\t\t{\n\t\t\t\"revealed\": false,\n\t\t\t\"cellId\": 42,\n\t\t\t\"row\": 4,\n\t\t\t\"userValue\": 0,\n\t\t\t\"col\": 6,\n\t\t\t\"realValue\": 0\n\t\t},\n\t\t{\n\t\t\t\"revealed\": false,\n\t\t\t\"cellId\": 43,\n\t\t\t\"row\": 4,\n\t\t\t\"userValue\": 0,\n\t\t\t\"col\": 7,\n\t\t\t\"realValue\": 0\n\t\t},\n\t\t{\n\t\t\t\"revealed\": false,\n\t\t\t\"cellId\": 44,\n\t\t\t\"row\": 4,\n\t\t\t\"userValue\": 0,\n\t\t\t\"col\": 8,\n\t\t\t\"realValue\": 0\n\t\t},\n\t\t{\n\t\t\t\"revealed\": false,\n\t\t\t\"cellId\": 45,\n\t\t\t\"row\": 5,\n\t\t\t\"userValue\": 0,\n\t\t\t\"col\": 0,\n\t\t\t\"realValue\": 0\n\t\t},\n\t\t{\n\t\t\t\"revealed\": false,\n\t\t\t\"cellId\": 46,\n\t\t\t\"row\": 5,\n\t\t\t\"userValue\": 0,\n\t\t\t\"col\": 1,\n\t\t\t\"realValue\": 0\n\t\t},\n\t\t{\n\t\t\t\"revealed\": false,\n\t\t\t\"cellId\": 47,\n\t\t\t\"row\": 5,\n\t\t\t\"userValue\": 0,\n\t\t\t\"col\": 2,\n\t\t\t\"realValue\": 0\n\t\t},\n\t\t{\n\t\t\t\"revealed\": false,\n\t\t\t\"cellId\": 48,\n\t\t\t\"row\": 5,\n\t\t\t\"userValue\": 0,\n\t\t\t\"col\": 3,\n\t\t\t\"realValue\": 0\n\t\t},\n\t\t{\n\t\t\t\"revealed\": false,\n\t\t\t\"cellId\": 49,\n\t\t\t\"row\": 5,\n\t\t\t\"userValue\": 0,\n\t\t\t\"col\": 4,\n\t\t\t\"realValue\": 0\n\t\t},\n\t\t{\n\t\t\t\"revealed\": false,\n\t\t\t\"cellId\": 50,\n\t\t\t\"row\": 5,\n\t\t\t\"userValue\": 0,\n\t\t\t\"col\": 5,\n\t\t\t\"realValue\": 0\n\t\t},\n\t\t{\n\t\t\t\"revealed\": false,\n\t\t\t\"cellId\": 51,\n\t\t\t\"row\": 5,\n\t\t\t\"userValue\": 0,\n\t\t\t\"col\": 6,\n\t\t\t\"realValue\": 0\n\t\t},\n\t\t{\n\t\t\t\"revealed\": false,\n\t\t\t\"cellId\": 52,\n\t\t\t\"row\": 5,\n\t\t\t\"userValue\": 0,\n\t\t\t\"col\": 7,\n\t\t\t\"realValue\": 0\n\t\t},\n\t\t{\n\t\t\t\"revealed\": false,\n\t\t\t\"cellId\": 53,\n\t\t\t\"row\": 5,\n\t\t\t\"userValue\": 0,\n\t\t\t\"col\": 8,\n\t\t\t\"realValue\": 0\n\t\t},\n\t\t{\n\t\t\t\"revealed\": false,\n\t\t\t\"cellId\": 54,\n\t\t\t\"row\": 6,\n\t\t\t\"userValue\": 0,\n\t\t\t\"col\": 0,\n\t\t\t\"realValue\": 0\n\t\t},\n\t\t{\n\t\t\t\"revealed\": false,\n\t\t\t\"cellId\": 55,\n\t\t\t\"row\": 6,\n\t\t\t\"userValue\": 0,\n\t\t\t\"col\": 1,\n\t\t\t\"realValue\": 0\n\t\t},\n\t\t{\n\t\t\t\"revealed\": false,\n\t\t\t\"cellId\": 56,\n\t\t\t\"row\": 6,\n\t\t\t\"userValue\": 0,\n\t\t\t\"col\": 2,\n\t\t\t\"realValue\": 0\n\t\t},\n\t\t{\n\t\t\t\"revealed\": false,\n\t\t\t\"cellId\": 57,\n\t\t\t\"row\": 6,\n\t\t\t\"userValue\": 0,\n\t\t\t\"col\": 3,\n\t\t\t\"realValue\": 0\n\t\t},\n\t\t{\n\t\t\t\"revealed\": false,\n\t\t\t\"cellId\": 58,\n\t\t\t\"row\": 6,\n\t\t\t\"userValue\": 0,\n\t\t\t\"col\": 4,\n\t\t\t\"realValue\": 0\n\t\t},\n\t\t{\n\t\t\t\"revealed\": false,\n\t\t\t\"cellId\": 59,\n\t\t\t\"row\": 6,\n\t\t\t\"userValue\": 0,\n\t\t\t\"col\": 5,\n\t\t\t\"realValue\": 0\n\t\t},\n\t\t{\n\t\t\t\"revealed\": false,\n\t\t\t\"cellId\": 60,\n\t\t\t\"row\": 6,\n\t\t\t\"userValue\": 0,\n\t\t\t\"col\": 6,\n\t\t\t\"realValue\": 0\n\t\t},\n\t\t{\n\t\t\t\"revealed\": false,\n\t\t\t\"cellId\": 61,\n\t\t\t\"row\": 6,\n\t\t\t\"userValue\": 0,\n\t\t\t\"col\": 7,\n\t\t\t\"realValue\": 0\n\t\t},\n\t\t{\n\t\t\t\"revealed\": false,\n\t\t\t\"cellId\": 62,\n\t\t\t\"row\": 6,\n\t\t\t\"userValue\": 0,\n\t\t\t\"col\": 8,\n\t\t\t\"realValue\": 0\n\t\t},\n\t\t{\n\t\t\t\"revealed\": false,\n\t\t\t\"cellId\": 63,\n\t\t\t\"row\": 7,\n\t\t\t\"userValue\": 0,\n\t\t\t\"col\": 0,\n\t\t\t\"realValue\": 0\n\t\t},\n\t\t{\n\t\t\t\"revealed\": false,\n\t\t\t\"cellId\": 64,\n\t\t\t\"row\": 7,\n\t\t\t\"userValue\": 0,\n\t\t\t\"col\": 1,\n\t\t\t\"realValue\": 0\n\t\t},\n\t\t{\n\t\t\t\"revealed\": false,\n\t\t\t\"cellId\": 65,\n\t\t\t\"row\": 7,\n\t\t\t\"userValue\": 0,\n\t\t\t\"col\": 2,\n\t\t\t\"realValue\": 0\n\t\t},\n\t\t{\n\t\t\t\"revealed\": false,\n\t\t\t\"cellId\": 66,\n\t\t\t\"row\": 7,\n\t\t\t\"userValue\": 0,\n\t\t\t\"col\": 3,\n\t\t\t\"realValue\": 0\n\t\t},\n\t\t{\n\t\t\t\"revealed\": false,\n\t\t\t\"cellId\": 67,\n\t\t\t\"row\": 7,\n\t\t\t\"userValue\": 0,\n\t\t\t\"col\": 4,\n\t\t\t\"realValue\": 0\n\t\t},\n\t\t{\n\t\t\t\"revealed\": false,\n\t\t\t\"cellId\": 68,\n\t\t\t\"row\": 7,\n\t\t\t\"userValue\": 0,\n\t\t\t\"col\": 5,\n\t\t\t\"realValue\": 0\n\t\t},\n\t\t{\n\t\t\t\"revealed\": false,\n\t\t\t\"cellId\": 69,\n\t\t\t\"row\": 7,\n\t\t\t\"userValue\": 0,\n\t\t\t\"col\": 6,\n\t\t\t\"realValue\": 0\n\t\t},\n\t\t{\n\t\t\t\"revealed\": false,\n\t\t\t\"cellId\": 70,\n\t\t\t\"row\": 7,\n\t\t\t\"userValue\": 0,\n\t\t\t\"col\": 7,\n\t\t\t\"realValue\": 0\n\t\t},\n\t\t{\n\t\t\t\"revealed\": false,\n\t\t\t\"cellId\": 71,\n\t\t\t\"row\": 7,\n\t\t\t\"userValue\": 0,\n\t\t\t\"col\": 8,\n\t\t\t\"realValue\": 0\n\t\t},\n\t\t{\n\t\t\t\"revealed\": false,\n\t\t\t\"cellId\": 72,\n\t\t\t\"row\": 8,\n\t\t\t\"userValue\": 0,\n\t\t\t\"col\": 0,\n\t\t\t\"realValue\": 0\n\t\t},\n\t\t{\n\t\t\t\"revealed\": false,\n\t\t\t\"cellId\": 73,\n\t\t\t\"row\": 8,\n\t\t\t\"userValue\": 0,\n\t\t\t\"col\": 1,\n\t\t\t\"realValue\": 0\n\t\t},\n\t\t{\n\t\t\t\"revealed\": false,\n\t\t\t\"cellId\": 74,\n\t\t\t\"row\": 8,\n\t\t\t\"userValue\": 0,\n\t\t\t\"col\": 2,\n\t\t\t\"realValue\": 0\n\t\t},\n\t\t{\n\t\t\t\"revealed\": false,\n\t\t\t\"cellId\": 75,\n\t\t\t\"row\": 8,\n\t\t\t\"userValue\": 0,\n\t\t\t\"col\": 3,\n\t\t\t\"realValue\": 0\n\t\t},\n\t\t{\n\t\t\t\"revealed\": false,\n\t\t\t\"cellId\": 76,\n\t\t\t\"row\": 8,\n\t\t\t\"userValue\": 0,\n\t\t\t\"col\": 4,\n\t\t\t\"realValue\": 0\n\t\t},\n\t\t{\n\t\t\t\"revealed\": false,\n\t\t\t\"cellId\": 77,\n\t\t\t\"row\": 8,\n\t\t\t\"userValue\": 0,\n\t\t\t\"col\": 5,\n\t\t\t\"realValue\": 0\n\t\t},\n\t\t{\n\t\t\t\"revealed\": false,\n\t\t\t\"cellId\": 78,\n\t\t\t\"row\": 8,\n\t\t\t\"userValue\": 0,\n\t\t\t\"col\": 6,\n\t\t\t\"realValue\": 0\n\t\t},\n\t\t{\n\t\t\t\"revealed\": false,\n\t\t\t\"cellId\": 79,\n\t\t\t\"row\": 8,\n\t\t\t\"userValue\": 0,\n\t\t\t\"col\": 7,\n\t\t\t\"realValue\": 0\n\t\t},\n\t\t{\n\t\t\t\"revealed\": false,\n\t\t\t\"cellId\": 80,\n\t\t\t\"row\": 8,\n\t\t\t\"userValue\": 0,\n\t\t\t\"col\": 8,\n\t\t\t\"realValue\": 0\n\t\t}\n\t]\n}"
			},
			"created": 1536955405509,
			"description": "",
			"headers": [
				{
					"disabled": false,
					"id": "pair_ca56df755e5944b29f1ea555b5be7095",
					"name": "Content-Type",
					"value": "application/json"
				}
			],
			"isPrivate": false,
			"metaSortKey": -1536955405509,
			"method": "PUT",
			"modified": 1537205771333,
			"name": "Save Grid",
			"parameters": [],
			"parentId": "wrk_51516313f77a4d3c9c686bb3d3fe2930",
			"settingDisableRenderRequestBody": false,
			"settingEncodeUrl": true,
			"settingMaxTimelineDataSize": 1000,
			"settingRebuildPath": true,
			"settingSendCookies": true,
			"settingStoreCookies": true,
			"url": "localhost:3000/grid/0",
			"_type": "request"
		},
		{
			"_id": "req_48d7766c29c341a6be7dbcd6b012f26b",
			"authentication": {},
			"body": {},
			"created": 1536955463612,
			"description": "",
			"headers": [],
			"isPrivate": false,
			"metaSortKey": -1536955463612,
			"method": "DELETE",
			"modified": 1537202254996,
			"name": "Delete Grid",
			"parameters": [],
			"parentId": "wrk_51516313f77a4d3c9c686bb3d3fe2930",
			"settingDisableRenderRequestBody": false,
			"settingEncodeUrl": true,
			"settingMaxTimelineDataSize": 1000,
			"settingRebuildPath": true,
			"settingSendCookies": true,
			"settingStoreCookies": true,
			"url": "localhost:3000/grid/1",
			"_type": "request"
		}
	]
}